accessdb/__init__.py
accessdb/access_api.py
accessdb/utils.py
accessdb-0.0.1.dist-info/LICENSE
accessdb-0.0.1.dist-info/METADATA
accessdb-0.0.1.dist-info/WHEEL
accessdb-0.0.1.dist-info/top_level.txt
accessdb-0.0.1.dist-info/RECORD
