Metadata-Version: 2.1
Name: accessdb
Version: 0.0.1
Summary: Fast way to create Access Database
Home-page: https://github.com/dhanababum/accessdb
Author: Dhana Babu
Author-email: dhana36.m@gmail.com
License: UNKNOWN
Download-URL: https://github.com/dhanababum/accessdb/archive/0.1.tar.gz
Keywords: python,accessdb,text
Platform: UNKNOWN
